SqliteQuanweiZhinan/README.md
SqliteQuanweiZhinan/__init__.py
SqliteQuanweiZhinan/__main__.py
SqliteQuanweiZhinan/file.epub
SqliteQuanweiZhinan/index.html
SqliteQuanweiZhinan/css/__init__.py
SqliteQuanweiZhinan/css/annotations.css
SqliteQuanweiZhinan/css/main.css
SqliteQuanweiZhinan/css/normalize.css
SqliteQuanweiZhinan/css/popup.css
SqliteQuanweiZhinan/font/__init__.py
SqliteQuanweiZhinan/font/fontello.eot
SqliteQuanweiZhinan/font/fontello.svg
SqliteQuanweiZhinan/font/fontello.ttf
SqliteQuanweiZhinan/font/fontello.woff
SqliteQuanweiZhinan/img/__init__.py
SqliteQuanweiZhinan/img/annotator-glyph-sprite.png
SqliteQuanweiZhinan/img/annotator-icon-sprite.png
SqliteQuanweiZhinan/img/apple-touch-icon.png
SqliteQuanweiZhinan/img/cancelfullscreen.png
SqliteQuanweiZhinan/img/close.png
SqliteQuanweiZhinan/img/fullscreen.png
SqliteQuanweiZhinan/img/loader.gif
SqliteQuanweiZhinan/img/menu-icon.png
SqliteQuanweiZhinan/img/save.png
SqliteQuanweiZhinan/img/saved.png
SqliteQuanweiZhinan/img/settings-s.png
SqliteQuanweiZhinan/img/settings.png
SqliteQuanweiZhinan/img/star.png
SqliteQuanweiZhinan/js/__init__.py
SqliteQuanweiZhinan/js/epub.js
SqliteQuanweiZhinan/js/epub.min.js
SqliteQuanweiZhinan/js/epub.min.map
SqliteQuanweiZhinan/js/hooks.min.js
SqliteQuanweiZhinan/js/hooks.min.map
SqliteQuanweiZhinan/js/reader.js
SqliteQuanweiZhinan/js/reader.js.map
SqliteQuanweiZhinan/js/reader.min.js
SqliteQuanweiZhinan/js/reader.min.map
SqliteQuanweiZhinan/js/hooks/__init__.py
SqliteQuanweiZhinan/js/hooks/extensions/__init__.py
SqliteQuanweiZhinan/js/hooks/extensions/highlight.js
SqliteQuanweiZhinan/js/libs/__init__.py
SqliteQuanweiZhinan/js/libs/jquery.min.js
SqliteQuanweiZhinan/js/libs/localforage.min.js
SqliteQuanweiZhinan/js/libs/screenfull.js
SqliteQuanweiZhinan/js/libs/screenfull.min.js
SqliteQuanweiZhinan/js/libs/zip.min.js
SqliteQuanweiZhinan/js/plugins/__init__.py
SqliteQuanweiZhinan/js/plugins/hypothesis.js
SqliteQuanweiZhinan/js/plugins/search.js
sqlite_quanwei_zhinan-2024.3.2.0.dist-info/METADATA
sqlite_quanwei_zhinan-2024.3.2.0.dist-info/WHEEL
sqlite_quanwei_zhinan-2024.3.2.0.dist-info/entry_points.txt
sqlite_quanwei_zhinan-2024.3.2.0.dist-info/top_level.txt
sqlite_quanwei_zhinan-2024.3.2.0.dist-info/RECORD
